orkestr8/__init__.py
orkestr8/en_q.py
orkestr8/en_q_client.py
orkestr8/installer.py
orkestr8/main.py
orkestr8/mock_train.py
orkestr8/settings.py
orkestr8/utils.py
orkestr8/clients/__init__.py
orkestr8/clients/data_lake_client.py
orkestr8/clients/protocol.py
orkestr8/clients/s3.py
orkestr8/commands/__init__.py
orkestr8/commands/base.py
orkestr8/commands/check.py
orkestr8/commands/download_model.py
orkestr8/commands/poll.py
orkestr8/commands/stop.py
orkestr8/commands/test.py
orkestr8/commands/train.py
orkestr8/commands/update.py
orkestr8/parsers/__init__.py
orkestr8/parsers/base_parser.py
orkestr8/parsers/check_parser.py
orkestr8/parsers/download_model_parser.py
orkestr8/parsers/mock_parser.py
orkestr8/parsers/poll_parser.py
orkestr8/parsers/run_parser.py
orkestr8/parsers/stop_parser.py
orkestr8/parsers/train_parser.py
orkestr8/parsers/update_parser.py
orkestr8_sdk-0.0.190.dist-info/METADATA
orkestr8_sdk-0.0.190.dist-info/WHEEL
orkestr8_sdk-0.0.190.dist-info/entry_points.txt
orkestr8_sdk-0.0.190.dist-info/top_level.txt
orkestr8_sdk-0.0.190.dist-info/RECORD
