Metadata-Version: 2.1
Name: orkestr8-sdk
Version: 0.0.190
Summary: SDK to easily interact with Orkestr8 ML entities
Author: Antsthebul
Requires-Python: >=3.8
Requires-Dist: python-dotenv
Requires-Dist: boto3
Provides-Extra: dev
Requires-Dist: pytest; extra == "dev"
Requires-Dist: pre-commit; extra == "dev"
Requires-Dist: pytest-cov; extra == "dev"
Requires-Dist: mypy; extra == "dev"
Requires-Dist: notebook; extra == "dev"
